odoo/addons/l10n_fr_cog/README.rst
odoo/addons/l10n_fr_cog/__init__.py
odoo/addons/l10n_fr_cog/__manifest__.py
odoo/addons/l10n_fr_cog/post_install.py
odoo/addons/l10n_fr_cog/data/country.xml
odoo/addons/l10n_fr_cog/i18n/l10n_fr_cog.pot
odoo/addons/l10n_fr_cog/models/__init__.py
odoo/addons/l10n_fr_cog/models/res_country.py
odoo/addons/l10n_fr_cog/readme/CONTRIBUTORS.rst
odoo/addons/l10n_fr_cog/readme/DESCRIPTION.rst
odoo/addons/l10n_fr_cog/static/description/icon.png
odoo/addons/l10n_fr_cog/static/description/index.html
odoo/addons/l10n_fr_cog/views/country.xml
odoo14_addon_l10n_fr_cog-14.0.1.1.0.dist-info/METADATA
odoo14_addon_l10n_fr_cog-14.0.1.1.0.dist-info/WHEEL
odoo14_addon_l10n_fr_cog-14.0.1.1.0.dist-info/top_level.txt
odoo14_addon_l10n_fr_cog-14.0.1.1.0.dist-info/RECORD
